{"url": "/class/view/12014", "timetable": [{"to": "2017-09-11 15:00:00", "from": "2017-09-11 13:15:00", "location": "25.3-005 - teori (80)"}, {"to": "2017-09-11 17:00:00", "from": "2017-09-11 15:15:00", "location": "25.3-005 - teori (80)"}, {"to": "2017-09-18 15:00:00", "from": "2017-09-18 13:15:00", "location": "25.3-005 - teori (80)"}, {"to": "2017-09-25 15:00:00", "from": "2017-09-25 13:15:00", "location": "25.3-005 - teori (80)"}, {"to": "2017-10-02 15:00:00", "from": "2017-10-02 13:15:00", "location": "25.3-005 - teori (80)"}, {"to": "2017-10-09 15:00:00", "from": "2017-10-09 13:15:00", "location": "25.3-005 - teori (80)"}, {"to": "2017-10-16 15:00:00", "from": "2017-10-16 13:15:00", "location": "25.3-005 - teori (80)"}, {"to": "2017-10-23 15:00:00", "from": "2017-10-23 13:15:00", "location": "25.3-005 - teori (80)"}, {"to": "2017-10-30 15:00:00", "from": "2017-10-30 13:15:00", "location": "25.3-005 - teori (80)"}, {"to": "2017-11-06 15:00:00", "from": "2017-11-06 13:15:00", "location": "25.3-005 - teori (80)"}, {"to": "2017-11-13 16:00:00", "from": "2017-11-13 13:15:00", "location": "25.3-005 - teori (80)"}, {"to": "2017-11-20 15:00:00", "from": "2017-11-20 13:15:00", "location": "25.3-005 - teori (80)"}, {"to": "2017-11-24 17:00:00", "from": "2017-11-22 17:00:00"}, {"to": "2018-01-17 16:00:00", "from": "2018-01-15 09:00:00"}, {"to": "2018-02-02 16:00:00", "from": "2018-02-02 09:00:00"}], "name": "Policyomr\u00e5der i et moderne demokrati: teori, analyse og organisation (Obligatorisk kursus)"}