{"url": "/class/view/12564", "timetable": [{"to": "2017-09-12 12:00:00", "from": "2017-09-12 10:15:00", "location": "45.2-051 - teorirum 45.2 (teorirum m. stoler\u00e6kker u. borde) (74)"}, {"to": "2017-09-19 12:00:00", "from": "2017-09-19 10:15:00", "location": "45.2-051 - teorirum 45.2 (teorirum m. stoler\u00e6kker u. borde) (74)"}, {"to": "2017-09-26 12:00:00", "from": "2017-09-26 10:15:00", "location": "45.2-051 - teorirum 45.2 (teorirum m. stoler\u00e6kker u. borde) (74)"}, {"to": "2017-10-03 12:00:00", "from": "2017-10-03 10:15:00", "location": "45.3-051 - teorirum m. stoler\u00e6kker (74)"}, {"to": "2017-10-10 12:00:00", "from": "2017-10-10 10:15:00", "location": "45.2-051 - teorirum 45.2 (teorirum m. stoler\u00e6kker u. borde) (74)"}, {"to": "2017-10-17 12:00:00", "from": "2017-10-17 10:15:00", "location": "45.2-051 - teorirum 45.2 (teorirum m. stoler\u00e6kker u. borde) (74)"}, {"to": "2017-10-24 12:00:00", "from": "2017-10-24 10:15:00", "location": "45.2-051 - teorirum 45.2 (teorirum m. stoler\u00e6kker u. borde) (74)"}, {"to": "2017-10-31 12:00:00", "from": "2017-10-31 10:15:00", "location": "45.2-051 - teorirum 45.2 (teorirum m. stoler\u00e6kker u. borde) (74)"}, {"to": "2018-01-09 12:00:00", "from": "2018-01-09 10:15:00", "location": "45.2-051 - teorirum 45.2 (teorirum m. stoler\u00e6kker u. borde) (74)"}, {"to": "2018-01-11 12:00:00", "from": "2018-01-09 12:00:00"}], "name": " Progressionskursus - Projektteknik - Hold: HAB-B-2017 (1. semester) "}